sos_notebook/__init__.py
sos_notebook/_version.py
sos_notebook/comm_manager.py
sos_notebook/completer.py
sos_notebook/converter.py
sos_notebook/inspector.py
sos_notebook/install.py
sos_notebook/kernel.js
sos_notebook/kernel.py
sos_notebook/logo-64x64.png
sos_notebook/magics.py
sos_notebook/step_executor.py
sos_notebook/subkernel.py
sos_notebook/test_utils.py
sos_notebook/workflow_executor.py
sos_notebook/templates/sos-cm-toc.tpl
sos_notebook/templates/sos-cm.tpl
sos_notebook/templates/sos-full-toc.tpl
sos_notebook/templates/sos-full.tpl
sos_notebook/templates/sos-markdown.tpl
sos_notebook/templates/sos-report-only-toc.tpl
sos_notebook/templates/sos-report-only.tpl
sos_notebook/templates/sos-report-toc-v2.tpl
sos_notebook/templates/sos-report-toc.tpl
sos_notebook/templates/sos-report-v1.tpl
sos_notebook/templates/sos-report-v2.tpl
sos_notebook/templates/sos-report.tpl
sos_notebook/templates/parts/cm.tpl
sos_notebook/templates/parts/control_panel.tpl
sos_notebook/templates/parts/control_panel_v1.tpl
sos_notebook/templates/parts/preview.tpl
sos_notebook/templates/parts/sos_style.tpl
sos_notebook/templates/parts/toc.tpl
sos_notebook/templates/sos-cm/conf.json
sos_notebook/templates/sos-cm/index.html.j2
sos_notebook/templates/sos-cm/sos-cm.html.j2
sos_notebook/templates/sos-cm/parts/cm.tpl
sos_notebook/templates/sos-cm/parts/sos-mode.js
sos_notebook/templates/sos-cm-toc/conf.json
sos_notebook/templates/sos-cm-toc/index.html.j2
sos_notebook/templates/sos-cm-toc/sos-cm-toc.html.j2
sos_notebook/templates/sos-cm-toc/parts/toc.tpl
sos_notebook/templates/sos-full/conf.json
sos_notebook/templates/sos-full/index.html.j2
sos_notebook/templates/sos-full/sos-full.html.j2
sos_notebook/templates/sos-full/parts/preview.tpl
sos_notebook/templates/sos-full/parts/sos_style.tpl
sos_notebook/templates/sos-full-toc/conf.json
sos_notebook/templates/sos-full-toc/index.html.j2
sos_notebook/templates/sos-full-toc/sos-full-toc.html.j2
sos_notebook/templates/sos-full-toc/parts/toc.tpl
sos_notebook-0.24.4.dist-info/LICENSE
sos_notebook-0.24.4.dist-info/METADATA
sos_notebook-0.24.4.dist-info/WHEEL
sos_notebook-0.24.4.dist-info/entry_points.txt
sos_notebook-0.24.4.dist-info/top_level.txt
sos_notebook-0.24.4.dist-info/RECORD
