Metadata-Version: 2.1
Name: sos-notebook
Version: 0.24.4
Summary: Script of Scripts (SoS): an interactive, cross-platform, and cross-language workflow system for reproducible data analysis
Home-page: https://github.com/vatlab/SOS
Author: Bo Peng
Author-email: Bo.Peng@bcm.edu
Maintainer: Bo Peng
Maintainer-email: Bo.Peng@bcm.edu
License: 3-clause BSD
Classifier: Development Status :: 4 - Beta
Classifier: Environment :: Console
Classifier: License :: OSI Approved :: BSD License
Classifier: Natural Language :: English
Classifier: Operating System :: POSIX :: Linux
Classifier: Operating System :: MacOS :: MacOS X
Classifier: Operating System :: Microsoft :: Windows
Classifier: Intended Audience :: Information Technology
Classifier: Intended Audience :: Science/Research
Classifier: Programming Language :: Python :: 3 :: Only
Classifier: Programming Language :: Python :: 3.7
Classifier: Programming Language :: Python :: 3.8
Classifier: Programming Language :: Python :: 3.9
Classifier: Programming Language :: Python :: Implementation :: CPython
Requires-Python: >=3.7
License-File: LICENSE
Requires-Dist: jupyter-client >=8.0.0
Requires-Dist: jupyter-core
Requires-Dist: sos >=0.22.0
Requires-Dist: nbformat
Requires-Dist: nbconvert >=6.0.1
Requires-Dist: ipython
Requires-Dist: ipykernel >=6.18.0
Requires-Dist: jinja2
Requires-Dist: notebook >=5.0.0
Requires-Dist: tabulate
Requires-Dist: pandas
Requires-Dist: numpy
Requires-Dist: psutil
